setup.cfg
setup.py
cloud_ftp/__init__.py
cloud_ftp/error.py
cloud_ftp.egg-info/PKG-INFO
cloud_ftp.egg-info/SOURCES.txt
cloud_ftp.egg-info/dependency_links.txt
cloud_ftp.egg-info/top_level.txt
cloud_ftp/api/__init__.py
cloud_ftp/api/v1/__init__.py
cloud_ftp/ftp/__init__.py
cloud_ftp/ftp/providers/__init__.py
cloud_ftp/ftp/providers/cloud_function.py
cloud_ftp/storage/__init__.py
cloud_ftp/storage/providers/__init__.py
cloud_ftp/storage/providers/gcs.py