Metadata-Version: 1.1
Name: cloud-ftp
Version: 1.0.1
Summary: Convenience wrapper for downloading FTP files on Google App Engine
Home-page: https://github.com/RealKinetic/cloud-ftp
Author: Real Kinetic
Author-email: dev@realkinetic.com
License: UNKNOWN
Download-URL: https://github.com/RealKinetic/cloud-ftp/archive/v1.0.1.tar.gz
Keywords: app engine,ftp
Platform: UNKNOWN
